config_inspector/__init__.py
config_inspector/manager.py
config_inspector/models.py
config_inspector/operations.py
config_inspector/protocols.py
config_inspector/registry.py
config_inspector/services.py
config_inspector/updaters.py
config_inspector-0.1.4.dist-info/licenses/AUTHORS.md
config_inspector-0.1.4.dist-info/licenses/LICENSE
config_inspector-0.1.4.dist-info/METADATA
config_inspector-0.1.4.dist-info/WHEEL
config_inspector-0.1.4.dist-info/top_level.txt
config_inspector-0.1.4.dist-info/RECORD
