Metadata-Version: 2.4
Name: config-inspector
Version: 0.1.4
Summary: Python package designed to help you manage and interact with text-based files in a robust and extensible way.
Author-email: Tim Santor <tsantor@xstudios.com>
Project-URL: Repository, https://bitbucket.org/xstudios/config-inspector.git
Project-URL: Issues, https://bitbucket.org/xstudios/config-inspector/issues
Project-URL: Changelog, https://bitbucket.org/xstudios/config-inspector/blob/master/HISTORY.md
Classifier: Development Status :: 5 - Production/Stable
Classifier: Environment :: Console
Classifier: Intended Audience :: Developers
Classifier: Natural Language :: English
Classifier: Programming Language :: Python :: 3.11
Classifier: Programming Language :: Python :: 3.12
Classifier: Programming Language :: Python :: 3.13
Classifier: Programming Language :: Python :: 3.14
Requires-Python: >=3.11
License-File: LICENSE
License-File: AUTHORS.md
Requires-Dist: requests>=2.32.5
Requires-Dist: toml>=0.10.2
Dynamic: license-file
